gradio_patch_selection/__init__.py
gradio_patch_selection/patch_selector.py
gradio_patch_selection/patch_selector.pyi
gradio_patch_selection/templates/component/index.js
gradio_patch_selection/templates/component/style.css
gradio_patch_selection/templates/example/index.js
gradio_patch_selection/templates/example/style.css
gradio_patch_selection-0.2.0.dist-info/METADATA
gradio_patch_selection-0.2.0.dist-info/WHEEL
gradio_patch_selection-0.2.0.dist-info/RECORD
