Metadata-Version: 2.4
Name: gradio_patch_selection
Version: 0.2.0
Summary: A Gradio component that allows users to select patches from images by overlaying a customizable grid.
Project-URL: Repository, https://github.com/dgcnz/gradio_patch_selector.git
Project-URL: Issues, https://github.com/dgcnz/gradio_patch_selector/issues
Author: Diego Canez
License-Expression: MIT
Keywords: attention-visualization,gradio-custom-component,gradio-template-Image,grid,patch-selector,transformer-visualization,vision-transformer,vit
Classifier: Development Status :: 3 - Alpha
Classifier: License :: OSI Approved :: Apache Software License
Classifier: Operating System :: OS Independent
Classifier: Programming Language :: Python :: 3
Classifier: Programming Language :: Python :: 3 :: Only
Classifier: Programming Language :: Python :: 3.8
Classifier: Programming Language :: Python :: 3.9
Classifier: Programming Language :: Python :: 3.10
Classifier: Programming Language :: Python :: 3.11
Classifier: Topic :: Scientific/Engineering
Classifier: Topic :: Scientific/Engineering :: Artificial Intelligence
Classifier: Topic :: Scientific/Engineering :: Visualization
Requires-Python: >=3.8
Requires-Dist: build>=1.2.2.post1
Requires-Dist: gradio<6.0,>=4.29
Requires-Dist: pip>=25.0.1
Provides-Extra: dev
Requires-Dist: build; extra == 'dev'
Requires-Dist: twine; extra == 'dev'
